{
  "name": "TruthChain",
  "manifestUrl": 'https://beocodez912.github.io/truthchain/tonconnect-manifest.json'
  "description": "Symbolic Blockchain + TON Wallet integration",
  "icon": "https://BeoCodez912.github.io/truthchain/icon.png",
  "homepage_url": "https://BeoCodez912.github.io/truthchain/",
  "developer_name": "BeoCodez912",
  "developer_url": "https://BeoCodez912.github.io/",
  "permissions": [
    "TON://TRANSFER",
    "TON://SIGN"
  ],
  "ton_network": "mainnet",
  "version": "1.0.0"
}

